aimon/__init__.py
aimon/_base_client.py
aimon/_client.py
aimon/_compat.py
aimon/_constants.py
aimon/_exceptions.py
aimon/_files.py
aimon/_models.py
aimon/_qs.py
aimon/_resource.py
aimon/_response.py
aimon/_streaming.py
aimon/_types.py
aimon/_version.py
aimon/py.typed
aimon/_utils/__init__.py
aimon/_utils/_logs.py
aimon/_utils/_proxy.py
aimon/_utils/_reflection.py
aimon/_utils/_resources_proxy.py
aimon/_utils/_streams.py
aimon/_utils/_sync.py
aimon/_utils/_transform.py
aimon/_utils/_typing.py
aimon/_utils/_utils.py
aimon/decorators/__init__.py
aimon/decorators/detect.py
aimon/decorators/evaluate.py
aimon/reprompting_api/__init__.py
aimon/reprompting_api/config.py
aimon/reprompting_api/pipeline.py
aimon/reprompting_api/reprompter.py
aimon/reprompting_api/runner.py
aimon/reprompting_api/telemetry.py
aimon/reprompting_api/utils.py
aimon/resources/__init__.py
aimon/resources/analyze.py
aimon/resources/inference.py
aimon/resources/metrics.py
aimon/resources/models.py
aimon/resources/retrieval.py
aimon/resources/users.py
aimon/resources/applications/__init__.py
aimon/resources/applications/applications.py
aimon/resources/applications/evaluations/__init__.py
aimon/resources/applications/evaluations/evaluations.py
aimon/resources/applications/evaluations/metrics.py
aimon/resources/applications/production/__init__.py
aimon/resources/applications/production/metrics.py
aimon/resources/applications/production/production.py
aimon/resources/datasets/__init__.py
aimon/resources/datasets/collection.py
aimon/resources/datasets/datasets.py
aimon/resources/datasets/records.py
aimon/resources/evaluations/__init__.py
aimon/resources/evaluations/evaluations.py
aimon/resources/evaluations/run.py
aimon/types/__init__.py
aimon/types/analyze_create_params.py
aimon/types/analyze_create_response.py
aimon/types/application_create_params.py
aimon/types/application_create_response.py
aimon/types/application_delete_params.py
aimon/types/application_delete_response.py
aimon-0.12.2.dist-info/licenses/LICENSE
aimon-0.12.2.dist-info/METADATA
aimon-0.12.2.dist-info/WHEEL
aimon-0.12.2.dist-info/top_level.txt
aimon-0.12.2.dist-info/RECORD
