Metadata-Version: 2.4
Name: aimon
Version: 0.12.2
Summary: The AIMon SDK that is used to interact with the AIMon API and the product.
Author: AIMon
Author-email: info@aimon.ai
Requires-Python: >3.8.0
License-File: LICENSE
Requires-Dist: annotated-types~=0.6.0
Requires-Dist: anyio~=4.9.0
Requires-Dist: certifi~=2025.4.26
Requires-Dist: distro~=1.9.0
Requires-Dist: exceptiongroup~=1.2.2
Requires-Dist: h11~=0.16.0
Requires-Dist: httpcore~=1.0.9
Requires-Dist: httpx<1.0.0,>=0.27.2
Requires-Dist: idna~=3.10
Requires-Dist: pydantic~=2.11.3
Requires-Dist: pydantic-core~=2.33.1
Requires-Dist: sniffio~=1.3.1
Requires-Dist: typing-extensions~=4.13.2
Dynamic: author
Dynamic: author-email
Dynamic: description
Dynamic: description-content-type
Dynamic: license-file
Dynamic: requires-dist
Dynamic: requires-python
Dynamic: summary
